MANIFEST.in
README.rst
setup.py
tastypie_redis/__init__.py
tastypie_redis/resources.py
tastypie_redis_resource.egg-info/PKG-INFO
tastypie_redis_resource.egg-info/SOURCES.txt
tastypie_redis_resource.egg-info/dependency_links.txt
tastypie_redis_resource.egg-info/not-zip-safe
tastypie_redis_resource.egg-info/requires.txt
tastypie_redis_resource.egg-info/top_level.txt