Metadata-Version: 1.1
Name: tastypie-redis-resource
Version: 0.0.2
Summary: Tastypie Redis Resource
Home-page: https://github.com/tunix/tastypie-redis-resource
Author: Alper Kanat
Author-email: tunix@raptiye.org
License: UNKNOWN
Keywords: tastypie rest api module resource redis
Platform: UNKNOWN
Classifier: Environment :: Console
Classifier: Environment :: Web Environment
Classifier: Framework :: Django
Classifier: Intended Audience :: Developers
Classifier: Natural Language :: English
Classifier: Programming Language :: Python
Classifier: Topic :: Internet
